{
  "generator-jhipster": {
    "applicationType": "monolith",
    "authenticationType": "jwt",
    "baseName": "PostCrud",
    "buildTool": "gradle",
    "cacheProvider": "ehcache",
    "clientFramework": "angular",
    "clientTheme": "none",
    "creationTimestamp": 1688809029912,
    "databaseType": "sql",
    "devDatabaseType": "postgresql",
    "devServerPort": 4200,
    "dtoSuffix": "DTO",
    "enableGradleEnterprise": null,
    "enableHibernateCache": false,
    "enableSwaggerCodegen": false,
    "enableTranslation": true,
    "entities": [],
    "entitySuffix": "",
    "gradleEnterpriseHost": null,
    "jhiPrefix": "jhi",
    "jhipsterVersion": "8.0.0-beta.1",
    "jwtSecretKey": "NmIyMDJmMDRhOWVlNmNiMmUzMzNjZmRkZDJjZjgwZDI3N2IwN2E3MGY2NDVhMGEwOTVhY2QzM2Y0ZjZhZDlhMDg1OTU1NDYxNzdmNjBkMGQ2Mzk5OTVjYzIxMzE1NmFmMDMyNTIwZTI4NjA3N2I1NjFlODZiOTFkMmEyYTgzMTk=",
    "languages": ["en", "fr", "bn"],
    "messageBroker": false,
    "microfrontend": false,
    "microfrontends": [],
    "nativeLanguage": "en",
    "packageFolder": "com/mamun/post",
    "packageName": "com.mamun.post",
    "pages": [],
    "prodDatabaseType": "postgresql",
    "reactive": false,
    "searchEngine": false,
    "serverPort": null,
    "serverSideOptions": [],
    "serviceDiscoveryType": false,
    "skipCheckLengthOfIdentifier": false,
    "skipClient": false,
    "skipFakeData": false,
    "skipUserManagement": false,
    "testFrameworks": [],
    "websocket": false,
    "withAdminUi": true
  }
}
